alfie/__init__.py
alfie/alf.py
alfie/classify.py
alfie/kmerseq.py
alfie/seqio.py
alfie/training.py
alfie/data/alfie.jpeg
alfie/data/dnn_model_4mers
alfie/data/dnn_model_6mers
alfie/data/example_data.fasta
alfie/data/example_data.fastq
alfie/tests/__init__.py
alfie/tests/test_classify.py
alfie/tests/test_kmerseq.py
alfie/tests/test_script.py
alfie/tests/test_seqio.py
alfie/tests/test_training.py
alfie-1.0.dist-info/LICENSE.md
alfie-1.0.dist-info/METADATA
alfie-1.0.dist-info/WHEEL
alfie-1.0.dist-info/entry_points.txt
alfie-1.0.dist-info/top_level.txt
alfie-1.0.dist-info/RECORD
