Metadata-Version: 2.1
Name: alfie
Version: 1.0
Summary: alignment free identification of edna
Home-page: https://github.com/CNuge/alfie
Author: Cam Nugent
Author-email: nugentc@uoguelph.ca
License: LICENSE.md
Platform: UNKNOWN
Requires-Python: >=3.6
Requires-Dist: numpy (>=1.18.1)
Requires-Dist: tensorflow (>=2.0.0)
Requires-Dist: scikit-learn (>=0.21.3)
Requires-Dist: pandas (>=0.25.1)
